byteclasses/__init__.py
byteclasses/_enums.py
byteclasses/constants.py
byteclasses/handlers/__init__.py
byteclasses/handlers/_data_handler.py
byteclasses/handlers/executables/__init__.py
byteclasses/handlers/executables/elf/__init__.py
byteclasses/handlers/executables/elf/dyn_entry.py
byteclasses/handlers/executables/elf/elf.py
byteclasses/handlers/executables/elf/elf_hdr.py
byteclasses/handlers/executables/elf/note_hdr.py
byteclasses/handlers/executables/elf/pentry.py
byteclasses/handlers/executables/elf/phdr.py
byteclasses/handlers/executables/elf/rel_entry.py
byteclasses/handlers/executables/elf/rela_entry.py
byteclasses/handlers/executables/elf/sentry.py
byteclasses/handlers/executables/elf/shdr.py
byteclasses/handlers/executables/elf/sym_entry.py
byteclasses/handlers/executables/mach/__init__.py
byteclasses/handlers/executables/mach/load_command.py
byteclasses/handlers/executables/mach/mach.py
byteclasses/handlers/executables/mach/mach_hdr.py
byteclasses/handlers/executables/mach/section.py
byteclasses/handlers/executables/mach/seg_cmd.py
byteclasses/handlers/executables/mach/uuid_cmd.py
byteclasses/handlers/executables/pe/__init__.py
byteclasses/handlers/executables/pe/data_dir.py
byteclasses/handlers/executables/pe/dos_hdr.py
byteclasses/handlers/executables/pe/file_hdr.py
byteclasses/handlers/executables/pe/nt_hdr32.py
byteclasses/handlers/executables/pe/nt_hdr64.py
byteclasses/handlers/executables/pe/opt_hdr32.py
byteclasses/handlers/executables/pe/opt_hdr64.py
byteclasses/handlers/executables/pe/pe.py
byteclasses/handlers/images/__init__.py
byteclasses/handlers/images/jpg/__init__.py
byteclasses/handlers/images/jpg/jpg.py
byteclasses/handlers/images/jpg/seg.py
byteclasses/handlers/network/__init__.py
byteclasses/handlers/network/eth_frame.py
byteclasses/handlers/network/eth_hdr.py
byteclasses/handlers/network/ipv4_hdr.py
byteclasses/handlers/network/ipv6_hdr.py
byteclasses/handlers/network/tcp_hdr.py
byteclasses/handlers/network/udp_hdr.py
byteclasses-0.6.0.dist-info/LICENSE
byteclasses-0.6.0.dist-info/METADATA
byteclasses-0.6.0.dist-info/WHEEL
byteclasses-0.6.0.dist-info/RECORD
