Metadata-Version: 2.1
Name: byteclasses
Version: 0.6.0
Summary: A python package designed for creating and managing blobs of binary data using dataclass like structures.
Home-page: https://github.com/thetacom/byteclasses
License: MIT
Keywords: struct,structures,binary,blobs,raw,bytes,dataclasses
Author: Justin C
Author-email: justin@thetacom.info
Requires-Python: >=3.10,<4.0
Classifier: Development Status :: 3 - Alpha
Classifier: Intended Audience :: Developers
Classifier: Intended Audience :: Information Technology
Classifier: Intended Audience :: Science/Research
Classifier: Intended Audience :: System Administrators
Classifier: License :: OSI Approved :: MIT License
Classifier: Natural Language :: English
Classifier: Operating System :: OS Independent
Classifier: Programming Language :: Python
Classifier: Programming Language :: Python :: 3
Classifier: Programming Language :: Python :: 3.10
Classifier: Programming Language :: Python :: 3.11
Classifier: Programming Language :: Python :: 3.12
Classifier: Programming Language :: Python :: 3 :: Only
Classifier: Programming Language :: Python :: Implementation :: CPython
Classifier: Topic :: Software Development :: Libraries
Requires-Dist: rich (>=13.7.1,<14.0.0)
Project-URL: Repository, https://github.com/thetacom/byteclasses
